setup.py
PyConstantsBase.egg-info/PKG-INFO
PyConstantsBase.egg-info/SOURCES.txt
PyConstantsBase.egg-info/dependency_links.txt
PyConstantsBase.egg-info/top_level.txt
pyConstants/__init__.py
pyConstants/constantBase.py
pyConstants/constantWrappers.py
pyConstantsBase.egg-info/PKG-INFO
pyConstantsBase.egg-info/SOURCES.txt
pyConstantsBase.egg-info/dependency_links.txt
pyConstantsBase.egg-info/top_level.txt